setup.py
sunnyday/__init__.py
sunnyday/sunnyday.py
sunnydays.egg-info/PKG-INFO
sunnydays.egg-info/SOURCES.txt
sunnydays.egg-info/dependency_links.txt
sunnydays.egg-info/requires.txt
sunnydays.egg-info/top_level.txt