Metadata-Version: 2.1
Name: sunnydays
Version: 1.1.0
Summary: Weather forecast data
Home-page: UNKNOWN
Author: hvppycoding
Author-email: hvppycoding@gmail.com
License: UNKNOWN
Keywords: weather,forecast,openweather
Platform: UNKNOWN
